cherpy-0.7.2.dist-info/METADATA
cherpy-0.7.2.dist-info/WHEEL
cherpy-0.7.2.dist-info/entry_points.txt
cherpy/__init__.py
cherpy/api.py
cherpy/auth.py
cherpy/cherwell.csv
cherpy/cli.py
cherpy/objects.py
cherpy/scripts/__init__.py
cherpy/test.csv
cherpy/utils.py
cherpy-0.7.2.dist-info/RECORD
