Metadata-Version: 2.1
Name: cherpy
Version: 0.7.2
Summary: A rest api wrapper for the Cherwell Service management platform
Author-Email: Josh Sarver <josh.sarver@gmail.com>
License: GNU GPLv3
Requires-Python: <4.0,>=3.9
Requires-Dist: requests<3.0.0,>=2.32.0
Requires-Dist: attrs<25.0.0,>=24.2.0
Requires-Dist: PyYAML<7.0.0,>=6.0.2
Requires-Dist: loguru<1.0.0,>=0.7.2
Requires-Dist: click<9.0.0,>=8.1.7
